{"is_source_file": false, "format": "", "description": "", "external_files": [], "external_methods": [], "published": [], "classes": [], "methods": [], "calls": [], "search-terms": ["CSS", "theme", "variables", "responsive", "media", "App"], "state": 2, "file_id": 10, "knowledge_revision": 28, "git_revision": "61fd2f85678bdbb55b789a8fd4b2a278426ef187", "hash": "22f9e17cc1848b56dbb244518ac2707e", "format-version": 4, "code-base-name": "tic_tac_toe_frontend", "filename": "tic_tac_toe_frontend/src/App.css", "revision_history": [{"28": "61fd2f85678bdbb55b789a8fd4b2a278426ef187"}]}